cve_explorer_cli/__init__.py
cve_explorer_cli/main.py
cve_explorer_cli/models/__init__.py
cve_explorer_cli/models/cve.py
cve_explorer_cli/models/cwe.py
cve_explorer_cli/models/epss.py
cve_explorer_cli/utilities/ext_request.py
cve_explorer_cli-0.3.1.dist-info/licenses/LICENSE
cve_explorer_cli-0.3.1.dist-info/METADATA
cve_explorer_cli-0.3.1.dist-info/WHEEL
cve_explorer_cli-0.3.1.dist-info/entry_points.txt
cve_explorer_cli-0.3.1.dist-info/top_level.txt
cve_explorer_cli-0.3.1.dist-info/RECORD
