Metadata-Version: 2.4
Name: cve-explorer-cli
Version: 0.3.1
Summary: View CVEs and related info with CLI interface
Author: Darrien Rushing
License-Expression: MIT
Project-URL: Homepage, https://github.com/meddlin/cve-explorer-cli
Requires-Python: >=3.11
License-File: LICENSE
Requires-Dist: certifi==2025.10.5
Requires-Dist: charset-normalizer==3.4.4
Requires-Dist: idna==3.11
Requires-Dist: requests==2.32.5
Requires-Dist: termcolor==3.1.0
Requires-Dist: urllib3==2.5.0
Requires-Dist: yaspin==3.3.0
Provides-Extra: dev
Requires-Dist: pytest>=8.0; extra == "dev"
Requires-Dist: build>=1.0.0; extra == "dev"
Requires-Dist: twine>=6.0.0; extra == "dev"
Dynamic: license-file
